rde_mcp_ros2/__init__.py
rde_mcp_ros2/server.py
rde_mcp_ros_2-1.0.1.dist-info/licenses/LICENSE
rde_mcp_ros_2-1.0.1.dist-info/METADATA
rde_mcp_ros_2-1.0.1.dist-info/WHEEL
rde_mcp_ros_2-1.0.1.dist-info/entry_points.txt
rde_mcp_ros_2-1.0.1.dist-info/top_level.txt
rde_mcp_ros_2-1.0.1.dist-info/RECORD
