Metadata-Version: 2.4
Name: rde-mcp-ros-2
Version: 1.0.1
Summary: Model Context Protocol server for ROS 2 introspection and control
Author-email: Ranch Hand Robotics <info@ranchhandrobotics.com>
License: MIT
Project-URL: Homepage, https://github.com/ranch-hand-robotics/rde-mcp-ros-2
Project-URL: Repository, https://github.com/ranch-hand-robotics/rde-mcp-ros-2
Project-URL: Bug Tracker, https://github.com/ranch-hand-robotics/rde-mcp-ros-2/issues
Keywords: ros2,mcp,model-context-protocol,ai,llm,robotics
Classifier: Development Status :: 4 - Beta
Classifier: Intended Audience :: Developers
Classifier: License :: OSI Approved :: MIT License
Classifier: Programming Language :: Python :: 3.12
Classifier: Topic :: Scientific/Engineering
Classifier: Topic :: Software Development :: Libraries :: Python Modules
Requires-Python: >=3.8
License-File: LICENSE
Requires-Dist: mcp[cli]>=1.12.3
Requires-Dist: pyyaml>=6.0
Requires-Dist: pydantic>=2.0
Requires-Dist: requests>=2.31.0
Requires-Dist: numpy>=1.20.0
Requires-Dist: jinja2>=3.0.0
Requires-Dist: setuptools>=61.0
Requires-Dist: typeguard>=4.0.0
Requires-Dist: lark-parser>=0.12.0
Provides-Extra: dev
Requires-Dist: pytest>=7.0; extra == "dev"
Requires-Dist: pytest-asyncio>=0.21.0; extra == "dev"
Requires-Dist: black>=23.0; extra == "dev"
Requires-Dist: ruff>=0.1.0; extra == "dev"
Requires-Dist: mypy>=1.0; extra == "dev"
Dynamic: license-file
